brewup/__init__.py
brewup/brewup.py
brewup/cli/__init__.py
brewup/cli/helpers.py
brewup/constants.py
brewup/default_config.toml
brewup/models/__init__.py
brewup/models/homebrew.py
brewup/models/package.py
brewup/utils/__init__.py
brewup/utils/common_utils.py
brewup/utils/config.py
brewup/utils/console.py
brewup/utils/logging.py
brewup/views/__init__.py
brewup/views/common.py
brewup-0.3.1.dist-info/LICENSE
brewup-0.3.1.dist-info/METADATA
brewup-0.3.1.dist-info/WHEEL
brewup-0.3.1.dist-info/entry_points.txt
brewup-0.3.1.dist-info/RECORD
