Metadata-Version: 2.1
Name: brewup
Version: 0.3.1
Summary: Ease common Homebrew commands
Home-page: https://github.com/natelandau/brewup
License: AGPL-3.0-or-later
Author: Nate Landauu
Author-email: github@natenate.org
Requires-Python: >=3.10,<4.0
Classifier: License :: OSI Approved :: GNU Affero General Public License v3 or later (AGPLv3+)
Classifier: Programming Language :: Python :: 3
Classifier: Programming Language :: Python :: 3.10
Classifier: Programming Language :: Python :: 3.11
Classifier: Programming Language :: Python :: 3.12
Requires-Dist: confz (>=2.0.1,<3.0.0)
Requires-Dist: loguru (>=0.7.2,<0.8.0)
Requires-Dist: questionary (>=2.0.1,<3.0.0)
Requires-Dist: rich (>=13.7.0,<14.0.0)
Requires-Dist: sh (>=2.0.6,<3.0.0)
Requires-Dist: typer[all] (>=0.9.0,<0.10.0)
Project-URL: Repository, https://github.com/natelandau/brewup
